kubeflow/__init__.py
kubeflow/metadata/__init__.py
kubeflow/metadata/metadata.py
kubeflow/metadata/openapi_client/__init__.py
kubeflow/metadata/openapi_client/api_client.py
kubeflow/metadata/openapi_client/configuration.py
kubeflow/metadata/openapi_client/exceptions.py
kubeflow/metadata/openapi_client/rest.py
kubeflow/metadata/openapi_client/api/__init__.py
kubeflow/metadata/openapi_client/api/metadata_service_api.py
kubeflow/metadata/openapi_client/models/__init__.py
kubeflow/metadata/openapi_client/models/api_create_artifact_response.py
kubeflow/metadata/openapi_client/models/api_create_artifact_type_response.py
kubeflow/metadata/openapi_client/models/api_create_execution_response.py
kubeflow/metadata/openapi_client/models/api_create_execution_type_response.py
kubeflow/metadata/openapi_client/models/api_get_artifact_response.py
kubeflow/metadata/openapi_client/models/api_get_artifact_type_response.py
kubeflow/metadata/openapi_client/models/api_get_execution_response.py
kubeflow/metadata/openapi_client/models/api_get_execution_type_response.py
kubeflow/metadata/openapi_client/models/api_list_artifact_types_response.py
kubeflow/metadata/openapi_client/models/api_list_artifacts_response.py
kubeflow/metadata/openapi_client/models/api_list_events_response.py
kubeflow/metadata/openapi_client/models/api_list_execution_types_response.py
kubeflow/metadata/openapi_client/models/api_list_executions_response.py
kubeflow/metadata/openapi_client/models/api_update_artifact_type_response.py
kubeflow/metadata/openapi_client/models/api_update_execution_type_response.py
kubeflow/metadata/openapi_client/models/event_path.py
kubeflow/metadata/openapi_client/models/ml_metadata_artifact.py
kubeflow/metadata/openapi_client/models/ml_metadata_artifact_struct_type.py
kubeflow/metadata/openapi_client/models/ml_metadata_artifact_type.py
kubeflow/metadata/openapi_client/models/ml_metadata_dict_artifact_struct_type.py
kubeflow/metadata/openapi_client/models/ml_metadata_event.py
kubeflow_metadata-0.2.0.dist-info/METADATA
kubeflow_metadata-0.2.0.dist-info/WHEEL
kubeflow_metadata-0.2.0.dist-info/top_level.txt
kubeflow_metadata-0.2.0.dist-info/RECORD
